jupyterlab_link_share/__init__.py
jupyterlab_link_share/_version.py
jupyterlab_link_share/handlers.py
jupyterlab_link_share/labextension/build_log.json
jupyterlab_link_share/labextension/package.json
jupyterlab_link_share/labextension/static/lib_index_js.6e353b15f3ac12b63b8e.js
jupyterlab_link_share/labextension/static/lib_index_js.6e353b15f3ac12b63b8e.js.map
jupyterlab_link_share/labextension/static/remoteEntry.baaa94ab8d652988bfff.js
jupyterlab_link_share/labextension/static/remoteEntry.baaa94ab8d652988bfff.js.map
jupyterlab_link_share/labextension/static/style.js
jupyterlab_link_share/labextension/static/style_index_js.e7915aaf967563326af7.js
jupyterlab_link_share/labextension/static/style_index_js.e7915aaf967563326af7.js.map
jupyterlab_link_share/labextension/static/vendors-node_modules_css-loader_dist_runtime_api_js-node_modules_css-loader_dist_runtime_cssW-926fd9.d6183d8565a8d998883e.js
jupyterlab_link_share/labextension/static/vendors-node_modules_css-loader_dist_runtime_api_js-node_modules_css-loader_dist_runtime_cssW-926fd9.d6183d8565a8d998883e.js.map
jupyterlab_link_share/labextension/static/vendors-node_modules_retrolab_application_lib_index_js.8bef599bfec9bd786f64.js
jupyterlab_link_share/labextension/static/vendors-node_modules_retrolab_application_lib_index_js.8bef599bfec9bd786f64.js.map
jupyterlab_link_share-0.3.0.data/data/etc/jupyter/jupyter_notebook_config.d/jupyterlab_link_share.json
jupyterlab_link_share-0.3.0.data/data/etc/jupyter/jupyter_server_config.d/jupyterlab_link_share.json
jupyterlab_link_share-0.3.0.data/data/share/jupyter/labextensions/jupyterlab-link-share/build_log.json
jupyterlab_link_share-0.3.0.data/data/share/jupyter/labextensions/jupyterlab-link-share/install.json
jupyterlab_link_share-0.3.0.data/data/share/jupyter/labextensions/jupyterlab-link-share/package.json
jupyterlab_link_share-0.3.0.data/data/share/jupyter/labextensions/jupyterlab-link-share/static/lib_index_js.6e353b15f3ac12b63b8e.js
jupyterlab_link_share-0.3.0.dist-info/LICENSE
jupyterlab_link_share-0.3.0.dist-info/METADATA
jupyterlab_link_share-0.3.0.dist-info/WHEEL
jupyterlab_link_share-0.3.0.dist-info/top_level.txt
jupyterlab_link_share-0.3.0.dist-info/RECORD
